arrow_udf/__init__.py
arrow_udf/test_udf.py
arrow_udf/udf/health_check.py
arrow_udf-0.3.1.dist-info/METADATA
arrow_udf-0.3.1.dist-info/WHEEL
arrow_udf-0.3.1.dist-info/top_level.txt
arrow_udf-0.3.1.dist-info/RECORD
