Metadata-Version: 2.4
Name: arrow-udf
Version: 0.3.1
Summary: A user-defined function framework for Apache Arrow
Author: RisingWave Labs
License: Apache Software License
Classifier: Programming Language :: Python
Classifier: License :: OSI Approved :: Apache Software License
Requires-Python: >=3.8
Requires-Dist: pyarrow<20,>=19
Provides-Extra: test
Requires-Dist: pytest; extra == "test"
